{
  "schema": "vela.proposal.v0.1",
  "id": "vpr_b965088659e1c798",
  "kind": "verifier.attach",
  "target": {
    "type": "finding",
    "id": "vf_e173d0be6bbcea46"
  },
  "actor": {
    "id": "agent:vela-verify",
    "type": "agent"
  },
  "created_at": "2026-06-17T06:37:48.750243+00:00",
  "reason": "backfill frozen verifier re-check",
  "payload": {
    "attachment": {
      "adversarial_probes": [
        {
          "kind": "counterexample_search",
          "result": "survived"
        }
      ],
      "claim_digest": "65d75176c6c513f4",
      "id": "vva_c4ce9810525dda9b",
      "independent_of": [],
      "match_to_claim": {
        "checker_actor": "vela-verify",
        "matches": true
      },
      "method_integrity": "sound",
      "note": "frozen verifier re-check: sidon",
      "outcome": "passed",
      "schema": "vela.verifier_attachment.v0.1",
      "solver_id": "vela-verify",
      "target": "vf_e173d0be6bbcea46",
      "verifier_actor": "vela-verify",
      "verifier_method": "computational_search"
    }
  },
  "source_refs": [],
  "status": "applied",
  "reviewed_by": "reviewer:will-blair",
  "reviewed_at": "2026-06-17T14:42:49.773571+00:00",
  "decision_reason": "maintainer accept: frozen-verifier re-check (vela-verify)",
  "applied_event_id": "vev_56e08d2c552a5ea3",
  "caveats": []
}